mixinsdk/__init__.py
mixinsdk/constants.py
mixinsdk/utils.py
mixinsdk/api/__init__.py
mixinsdk/api/address.py
mixinsdk/api/asset.py
mixinsdk/api/conversation.py
mixinsdk/api/message.py
mixinsdk/api/multisig.py
mixinsdk/api/network.py
mixinsdk/api/pin.py
mixinsdk/api/transfer.py
mixinsdk/api/user.py
mixinsdk/api/withdrawal.py
mixinsdk/clients/__init__.py
mixinsdk/clients/_message.py
mixinsdk/clients/_requests.py
mixinsdk/clients/_sign.py
mixinsdk/clients/client_blaze.py
mixinsdk/clients/client_http.py
mixinsdk/clients/client_http_nosign.py
mixinsdk/clients/config.py
mixinsdk/rpc/__init__.py
mixinsdk/types/__init__.py
mixinsdk/types/errors.py
mixinsdk/types/message.py
mixinsdk/types/messenger_schema.py
mixinsdk/types/transfer.py
mixinsdk/types/user.py
mixinsdk-0.2.1.dist-info/LICENSE
mixinsdk-0.2.1.dist-info/METADATA
mixinsdk-0.2.1.dist-info/WHEEL
mixinsdk-0.2.1.dist-info/top_level.txt
mixinsdk-0.2.1.dist-info/RECORD
