Metadata-Version: 2.1
Name: mixinsdk
Version: 0.2.1
Summary: python sdk for mixin: https://github.com/nodewee/mixin-sdk-python
Home-page: https://github.com/nodewee/mixin-sdk-python
Author: nodewee
Author-email: nodewee@gmail.com
Project-URL: Github Repo, https://github.com/nodewee/mixin-sdk-python
Project-URL: Bug Tracker, https://github.com/nodewee/mixin-sdk-python/issues
Project-URL: About Mixin, https://developers.mixin.one/
Keywords: mixin,python,sdk,api,mixin network
Classifier: Programming Language :: Python :: 3
Classifier: Programming Language :: Python :: 3.9
Classifier: License :: OSI Approved :: MIT License
Classifier: Operating System :: OS Independent
Requires-Python: >=3.9
License-File: LICENSE
Requires-Dist: requests
Requires-Dist: pyjwt
Requires-Dist: cryptography
Requires-Dist: pynacl
Requires-Dist: httpx
Requires-Dist: websockets
Requires-Dist: dacite
